dchpythonlibrary/__init__.py
dchpythonlibrary/myfunctions.py
Dchlib-0.0.1.dist-info/METADATA
Dchlib-0.0.1.dist-info/WHEEL
Dchlib-0.0.1.dist-info/top_level.txt
Dchlib-0.0.1.dist-info/RECORD
