Metadata-Version: 2.1
Name: Dchlib
Version: 0.0.1
Summary: Python Test Library
Home-page: UNKNOWN
Author: David Chincharashvili
Author-email: davit.chincharashvili.1@iliauni.edu.ge
License: MIT
Platform: UNKNOWN
